<?xml version="1.0" encoding="UTF-8"?><retConsReciNFe versao="3.10" xmlns="http://www.portalfiscal.inf.br/nfe"><tpAmb>2</tpAmb><verAplic>SVRSnfce201711011218</verAplic><nRec>293065042749288</nRec><cStat>104</cStat><xMotivo>Lote processado</xMotivo><cUF>29</cUF><dhRecbto>2017-11-24T02:28:04-03:00</dhRecbto><protNFe versao="3.10"><infProt><tpAmb>2</tpAmb><verAplic>SVRSnfce201711011218</verAplic><chNFe>29171112319813000209650010000000211000000212</chNFe><dhRecbto>2017-11-24T02:28:04-03:00</dhRecbto><digVal>dC0EAohK1LA2YF+mDnJVHB6Evwk=</digVal><cStat>462</cStat><xMotivo>Rejeicao: Codigo identificador do CSC no QR-Code nao cadastrado na SEFAZ</xMotivo></infProt></protNFe></retConsReciNFe>